jobspec/__init__.py
jobspec/defaults.py
jobspec/logger.py
jobspec/runner.py
jobspec/schema.py
jobspec/transform.py
jobspec/utils.py
jobspec/version.py
jobspec/cli/__init__.py
jobspec/cli/run.py
jobspec/cli/satisfy.py
jobspec/core/__init__.py
jobspec/core/base.py
jobspec/core/converter.py
jobspec/core/core.py
jobspec/core/resources.py
jobspec/core/v1.py
jobspec/logger/__init__.py
jobspec/logger/generate.py
jobspec/logger/logger.py
jobspec/plugin/__init__.py
jobspec/plugin/registry.py
jobspec/steps/__init__.py
jobspec/steps/base.py
jobspec/steps/empty.py
jobspec/steps/fileio.py
jobspec/steps/helpers.py
jobspec/steps/runner.py
jobspec/subsystem/__init__.py
jobspec/subsystem/queries.py
jobspec/subsystem/subsystem.py
jobspec/transformer/__init__.py
jobspec/transformer/base.py
jobspec/transformer/flux.py
jobspec/transformer/registry.py
jobspec/transformer/result.py
jobspec/transformer/flux/__init__.py
jobspec/transformer/flux/steps.py
jobspec/transformer/flux/workload.py
jobspec-0.1.15.dist-info/LICENSE
jobspec-0.1.15.dist-info/METADATA
jobspec-0.1.15.dist-info/NOTICE
jobspec-0.1.15.dist-info/WHEEL
jobspec-0.1.15.dist-info/entry_points.txt
jobspec-0.1.15.dist-info/top_level.txt
jobspec-0.1.15.dist-info/RECORD
